peace_for_gaza/__init__.py
peace_for_gaza/peace_for_gaza.py
peace_for_gaza-0.1.dist-info/METADATA
peace_for_gaza-0.1.dist-info/WHEEL
peace_for_gaza-0.1.dist-info/entry_points.txt
peace_for_gaza-0.1.dist-info/top_level.txt
peace_for_gaza-0.1.dist-info/RECORD
