Metadata-Version: 2.1
Name: peace_for_gaza
Version: 0.1
Home-page: https://github.com/peace-and-love-py/peace_for_gaza
